macpyver_fortigate_source/__init__.py
macpyver_fortigate_source/exceptions.py
macpyver_fortigate_source/fortigate_source.py
macpyver_fortigate_source/py.typed
macpyver_fortigate_source-1.0.0.dist-info/LICENSE.md
macpyver_fortigate_source-1.0.0.dist-info/METADATA
macpyver_fortigate_source-1.0.0.dist-info/WHEEL
macpyver_fortigate_source-1.0.0.dist-info/RECORD
