Metadata-Version: 2.1
Name: macpyver_fortigate_source
Version: 1.0.0
Summary: Version Source for FortiGates for MacPyVer.
License: MIT
Author: Daryl Stark
Author-email: daryl@dstark.nl
Requires-Python: >=3.10,<4.0
Classifier: License :: OSI Approved :: MIT License
Classifier: Programming Language :: Python :: 3
Classifier: Programming Language :: Python :: 3.10
Classifier: Programming Language :: Python :: 3.11
Classifier: Programming Language :: Python :: 3.12
Requires-Dist: macpyver-core (>=1.0.0,<2.0.0)
Requires-Dist: requests (>=2.31.0,<3.0.0)
